frost_forge/__init__.py
frost_forge/__main__.py
frost_forge/rendering.py
frost_forge/update.py
frost_forge/info/__init__.py
frost_forge/info/achievement.py
frost_forge/info/render.py
frost_forge/info/general_tile/attribute.py
frost_forge/info/general_tile/health.py
frost_forge/info/general_tile/resistance.py
frost_forge/info/general_tile/tool.py
frost_forge/info/specific_tile/accessory.py
frost_forge/info/specific_tile/description.py
frost_forge/info/specific_tile/entity.py
frost_forge/info/specific_tile/floor.py
frost_forge/info/specific_tile/growth.py
frost_forge/info/specific_tile/item.py
frost_forge/info/specific_tile/recipes.py
frost_forge/info/specific_tile/tile.py
frost_forge/info/specific_tile/value.py
frost_forge/info/world_gen/loot_table.py
frost_forge/info/world_gen/structure_gen.py
frost_forge/info/world_gen/world_gen.py
frost_forge/other_systems/game_saving.py
frost_forge/other_systems/game_state.py
frost_forge/other_systems/settings_saving.py
frost_forge/other_systems/tile_placable.py
frost_forge/other_systems/tile_placement.py
frost_forge/other_systems/walk.py
frost_forge/render/game_rendering/__init__.py
frost_forge/render/game_rendering/ghost_rendering.py
frost_forge/render/game_rendering/hand_rendering.py
frost_forge/render/game_rendering/map_rendering.py
frost_forge/render/game_rendering/mine_rendering.py
frost_forge/render/main_rendering/__init__.py
frost_forge/render/main_rendering/game_rendering.py
frost_forge/render/main_rendering/menu_rendering.py
frost_forge/render/main_rendering/menu_text.py
frost_forge/render/main_rendering/ui_rendering.py
frost_forge/render/user_interface_rendering/__init__.py
frost_forge/render/user_interface_rendering/accessory_rendering.py
frost_forge/render/user_interface_rendering/achievement_rendering.py
frost_forge/render/user_interface_rendering/craft_rendering.py
frost_forge/render/user_interface_rendering/description_rendering.py
frost_forge/render/user_interface_rendering/health_rendering.py
frost_forge-0.3.0.dist-info/METADATA
frost_forge-0.3.0.dist-info/WHEEL
frost_forge-0.3.0.dist-info/entry_points.txt
frost_forge-0.3.0.dist-info/licenses/LICENSE
frost_forge-0.3.0.dist-info/RECORD
