Metadata-Version: 2.3
Name: frost-forge
Version: 0.3.0
Summary: A sandbox game with procedual world generation, mining, building, and crafting
Author-email: TimoAndy08 <134264827+TimoAndy08@users.noreply.github.com>
License: MIT License
Requires-Python: >=3.13
Requires-Dist: noise~=1.2.2
Requires-Dist: pillow~=11.3.0
Requires-Dist: pygame~=2.6
